Css3Jiaocheng7TianKuaisuRumenCYuyanZhongwenwang/README.md
Css3Jiaocheng7TianKuaisuRumenCYuyanZhongwenwang/__init__.py
Css3Jiaocheng7TianKuaisuRumenCYuyanZhongwenwang/__main__.py
Css3Jiaocheng7TianKuaisuRumenCYuyanZhongwenwang/file.epub
Css3Jiaocheng7TianKuaisuRumenCYuyanZhongwenwang/index.html
Css3Jiaocheng7TianKuaisuRumenCYuyanZhongwenwang/css/__init__.py
Css3Jiaocheng7TianKuaisuRumenCYuyanZhongwenwang/css/annotations.css
Css3Jiaocheng7TianKuaisuRumenCYuyanZhongwenwang/css/main.css
Css3Jiaocheng7TianKuaisuRumenCYuyanZhongwenwang/css/normalize.css
Css3Jiaocheng7TianKuaisuRumenCYuyanZhongwenwang/css/popup.css
Css3Jiaocheng7TianKuaisuRumenCYuyanZhongwenwang/font/__init__.py
Css3Jiaocheng7TianKuaisuRumenCYuyanZhongwenwang/font/fontello.eot
Css3Jiaocheng7TianKuaisuRumenCYuyanZhongwenwang/font/fontello.svg
Css3Jiaocheng7TianKuaisuRumenCYuyanZhongwenwang/font/fontello.ttf
Css3Jiaocheng7TianKuaisuRumenCYuyanZhongwenwang/font/fontello.woff
Css3Jiaocheng7TianKuaisuRumenCYuyanZhongwenwang/img/__init__.py
Css3Jiaocheng7TianKuaisuRumenCYuyanZhongwenwang/img/annotator-glyph-sprite.png
Css3Jiaocheng7TianKuaisuRumenCYuyanZhongwenwang/img/annotator-icon-sprite.png
Css3Jiaocheng7TianKuaisuRumenCYuyanZhongwenwang/img/apple-touch-icon.png
Css3Jiaocheng7TianKuaisuRumenCYuyanZhongwenwang/img/cancelfullscreen.png
Css3Jiaocheng7TianKuaisuRumenCYuyanZhongwenwang/img/close.png
Css3Jiaocheng7TianKuaisuRumenCYuyanZhongwenwang/img/fullscreen.png
Css3Jiaocheng7TianKuaisuRumenCYuyanZhongwenwang/img/loader.gif
Css3Jiaocheng7TianKuaisuRumenCYuyanZhongwenwang/img/menu-icon.png
Css3Jiaocheng7TianKuaisuRumenCYuyanZhongwenwang/img/save.png
Css3Jiaocheng7TianKuaisuRumenCYuyanZhongwenwang/img/saved.png
Css3Jiaocheng7TianKuaisuRumenCYuyanZhongwenwang/img/settings-s.png
Css3Jiaocheng7TianKuaisuRumenCYuyanZhongwenwang/img/settings.png
Css3Jiaocheng7TianKuaisuRumenCYuyanZhongwenwang/img/star.png
Css3Jiaocheng7TianKuaisuRumenCYuyanZhongwenwang/js/__init__.py
css3_jiaocheng_7_tian_kuaisu_rumen_c_yuyan_zhongwenwang-2024.3.5.0.dist-info/METADATA
css3_jiaocheng_7_tian_kuaisu_rumen_c_yuyan_zhongwenwang-2024.3.5.0.dist-info/WHEEL
css3_jiaocheng_7_tian_kuaisu_rumen_c_yuyan_zhongwenwang-2024.3.5.0.dist-info/entry_points.txt
css3_jiaocheng_7_tian_kuaisu_rumen_c_yuyan_zhongwenwang-2024.3.5.0.dist-info/top_level.txt
css3_jiaocheng_7_tian_kuaisu_rumen_c_yuyan_zhongwenwang-2024.3.5.0.dist-info/RECORD
